kickbase_api/__init__.py
kickbase_api/exceptions.py
kickbase_api/kickbase.py
kickbase_api/models/__init__.py
kickbase_api/models/_transforms.py
kickbase_api/models/base_model.py
kickbase_api/models/chat_item.py
kickbase_api/models/feed_item.py
kickbase_api/models/feed_item_comment.py
kickbase_api/models/feed_meta.py
kickbase_api/models/gift.py
kickbase_api/models/league_data.py
kickbase_api/models/league_info.py
kickbase_api/models/league_match_day_stats_data.py
kickbase_api/models/league_match_day_user_stats.py
kickbase_api/models/league_me.py
kickbase_api/models/league_user_data.py
kickbase_api/models/league_user_profile.py
kickbase_api/models/league_user_profile_season_stats.py
kickbase_api/models/league_user_season_stats.py
kickbase_api/models/league_user_stats.py
kickbase_api/models/lineup.py
kickbase_api/models/market.py
kickbase_api/models/market_player.py
kickbase_api/models/market_player_offer.py
kickbase_api/models/player.py
kickbase_api/models/user.py
kickbase_api/models/response/__init__.py
kickbase_api/models/response/league_stats_response.py
Kickbase_API-0.0.8.dist-info/LICENSE
Kickbase_API-0.0.8.dist-info/METADATA
Kickbase_API-0.0.8.dist-info/WHEEL
Kickbase_API-0.0.8.dist-info/top_level.txt
Kickbase_API-0.0.8.dist-info/RECORD
