Metadata-Version: 2.1
Name: Kickbase_API
Version: 0.0.8
Summary: Python API library for kickbase
Home-page: https://github.com/kevinskyba/kickbase-api-python
Author: kevinskyba
Author-email: kevinskyba@live.de
License: MIT
Platform: UNKNOWN
